LICENSE
MANIFEST.in
README.md
install_binaries.py
setup.py
install_binaries.egg-info/PKG-INFO
install_binaries.egg-info/SOURCES.txt
install_binaries.egg-info/dependency_links.txt
install_binaries.egg-info/entry_points.txt
install_binaries.egg-info/top_level.txt