Metadata-Version: 1.1
Name: install-binaries
Version: 0.4.1
Summary: Install binaries to the same place Python would install scripts.
Home-page: https://github.com/tgs/install-binaries
Author: Thomas Grenfell Smith
Author-email: smithtg@ncbi.nlm.nih.gov
License: UNKNOWN
Platform: UNKNOWN
Classifier: License :: Public Domain
Classifier: Programming Language :: Python :: 2
Classifier: Programming Language :: Python :: 3
Classifier: Topic :: Software Development
Classifier: Intended Audience :: Developers
Classifier: Development Status :: 4 - Beta
